smartclim_ble/__init__.py
smartclim_ble/const.py
smartclim_ble/parser.py
smartclim_ble/py.typed
beewi_smartclim_ble-0.4.0.dist-info/LICENSE
beewi_smartclim_ble-0.4.0.dist-info/METADATA
beewi_smartclim_ble-0.4.0.dist-info/WHEEL
beewi_smartclim_ble-0.4.0.dist-info/RECORD
