Metadata-Version: 2.1
Name: beewi-smartclim-ble
Version: 0.4.0
Summary: Parser for the BeeWi SmartClim device
Home-page: https://github.com/f-davin/hassis_beewi_smartclim.git
License: MIT
Author: f-davin
Author-email: none@none.com
Requires-Python: >=3.9,<4.0
Classifier: Development Status :: 2 - Pre-Alpha
Classifier: Intended Audience :: Developers
Classifier: License :: OSI Approved :: MIT License
Classifier: Natural Language :: English
Classifier: Operating System :: OS Independent
Classifier: Programming Language :: Python :: 3
Classifier: Programming Language :: Python :: 3.9
Classifier: Programming Language :: Python :: 3.10
Classifier: Programming Language :: Python :: 3.11
Classifier: Topic :: Software Development :: Libraries
Provides-Extra: docs
Requires-Dist: Sphinx (>=5.0,<6.0) ; extra == "docs"
Requires-Dist: bleak (>=0.19.5)
Requires-Dist: bleak-retry-connector (>=2.13.0)
Requires-Dist: bluetooth-data-tools (>=0.3.1)
Requires-Dist: bluetooth-sensor-state-data (>=1.6.0)
Requires-Dist: home-assistant-bluetooth (>=1.9.2)
Requires-Dist: myst-parser (>=0.18,<0.19) ; extra == "docs"
Requires-Dist: sensor-state-data (>=2.17.1)
Requires-Dist: sphinx-rtd-theme (>=1.0,<2.0) ; extra == "docs"
Project-URL: Bug Tracker, https://github.com/f-davin/hassis_beewi_smartclim/issues
Project-URL: Changelog, https://github.com/f-davin/hassis_beewi_smartclim/blob/main/CHANGELOG.md
Project-URL: Repository, https://github.com/f-davin/hassis_beewi_smartclim.git
